QuickProject/Commander.py
QuickProject/Qpro.py
QuickProject/QproFigTable.py
QuickProject/QproZshComp.py
QuickProject/__config__.py
QuickProject/__init__.py
QuickProject/lang.json
QuickProject/qrun.py
QuickProject/ssh.py
qpro-0.13.9.dist-info/LICENSE
qpro-0.13.9.dist-info/METADATA
qpro-0.13.9.dist-info/WHEEL
qpro-0.13.9.dist-info/entry_points.txt
qpro-0.13.9.dist-info/RECORD
