Metadata-Version: 2.3
Name: qpro
Version: 0.13.9
Summary: Small but powerful command line APP framework
License: MIT
Author: Rhythmicc
Author-email: rhythmlian.cn@gmail.com
Requires-Python: >=3.7,<4.0
Classifier: License :: OSI Approved :: MIT License
Classifier: Programming Language :: Python :: 3
Classifier: Programming Language :: Python :: 3.7
Classifier: Programming Language :: Python :: 3.8
Classifier: Programming Language :: Python :: 3.9
Classifier: Programming Language :: Python :: 3.10
Classifier: Programming Language :: Python :: 3.11
Classifier: Programming Language :: Python :: 3.12
Classifier: Programming Language :: Python :: 3.13
Requires-Dist: GitPython (>=3.1.32,<4.0.0)
Requires-Dist: inquirer-rhy (>=0.1.2,<0.2.0)
Requires-Dist: langsrc (>=0.0.8,<0.0.9)
Requires-Dist: pyperclip (>=1.8.2,<2.0.0)
Requires-Dist: rich (>=13.3.5,<14.0.0)
Requires-Dist: toml (>=0.10.2,<0.11.0)
